my_package_alina/__init__.py
my_package_alina/main.py
my_package_alina-0.1.0.dist-info/METADATA
my_package_alina-0.1.0.dist-info/WHEEL
my_package_alina-0.1.0.dist-info/top_level.txt
my_package_alina-0.1.0.dist-info/RECORD
