Metadata-Version: 2.4
Name: my-package-alina
Version: 0.1.0
Summary: My sample project
Author-email: Alina <alina@email.com>
License: MIT
Requires-Python: >=3.12
